[
  {
    "ContainingType": "NotesAPI.Controllers.NoteController",
    "Method": "GetLists",
    "RelativePath": "lists",
    "HttpMethod": "GET",
    "IsController": true,
    "Order": 0,
    "Parameters": [],
    "ReturnTypes": []
  },
  {
    "ContainingType": "NotesAPI.Controllers.NoteController",
    "Method": "DeleteList",
    "RelativePath": "lists/delete/{id}",
    "HttpMethod": "DELETE",
    "IsController": true,
    "Order": 0,
    "Parameters": [
      {
        "Name": "id",
        "Type": "System.Guid",
        "IsRequired": true
      }
    ],
    "ReturnTypes": []
  },
  {
    "ContainingType": "NotesAPI.Controllers.UserController",
    "Method": "Login",
    "RelativePath": "login",
    "HttpMethod": "POST",
    "IsController": true,
    "Order": 0,
    "Parameters": [
      {
        "Name": "request",
        "Type": "NotesEntities.LoginUserRequest",
        "IsRequired": true
      }
    ],
    "ReturnTypes": []
  },
  {
    "ContainingType": "NotesAPI.Controllers.NoteController",
    "Method": "GetNotes",
    "RelativePath": "notes",
    "HttpMethod": "GET",
    "IsController": true,
    "Order": 0,
    "Parameters": [],
    "ReturnTypes": []
  },
  {
    "ContainingType": "NotesAPI.Controllers.NoteController",
    "Method": "GetNoteById",
    "RelativePath": "notes/{id}",
    "HttpMethod": "GET",
    "IsController": true,
    "Order": 0,
    "Parameters": [
      {
        "Name": "id",
        "Type": "System.Guid",
        "IsRequired": true
      }
    ],
    "ReturnTypes": []
  },
  {
    "ContainingType": "NotesAPI.Controllers.NoteController",
    "Method": "CreateNote",
    "RelativePath": "notes/create",
    "HttpMethod": "POST",
    "IsController": true,
    "Order": 0,
    "Parameters": [
      {
        "Name": "note",
        "Type": "NotesEntities.CreateNote",
        "IsRequired": true
      }
    ],
    "ReturnTypes": []
  },
  {
    "ContainingType": "NotesAPI.Controllers.NoteController",
    "Method": "DeleteNote",
    "RelativePath": "notes/delete/{id}",
    "HttpMethod": "DELETE",
    "IsController": true,
    "Order": 0,
    "Parameters": [
      {
        "Name": "id",
        "Type": "System.Guid",
        "IsRequired": true
      }
    ],
    "ReturnTypes": []
  },
  {
    "ContainingType": "NotesAPI.Controllers.NoteController",
    "Method": "UpdateNote",
    "RelativePath": "notes/update/{id}",
    "HttpMethod": "PUT",
    "IsController": true,
    "Order": 0,
    "Parameters": [
      {
        "Name": "note",
        "Type": "NotesEntities.Note",
        "IsRequired": true
      },
      {
        "Name": "id",
        "Type": "System.Guid",
        "IsRequired": true
      }
    ],
    "ReturnTypes": []
  },
  {
    "ContainingType": "NotesAPI.Controllers.UserController",
    "Method": "Register",
    "RelativePath": "register",
    "HttpMethod": "POST",
    "IsController": true,
    "Order": 0,
    "Parameters": [
      {
        "Name": "request",
        "Type": "NotesEntities.RegisterUserRequest",
        "IsRequired": true
      }
    ],
    "ReturnTypes": []
  }
]